otlet_test_project/__init__.py
otlet_test_project-0.0.4.dist-info/WHEEL
otlet_test_project-0.0.4.dist-info/METADATA
otlet_test_project-0.0.4.dist-info/RECORD
